EMIZ-2018.9.16.4.dist-info/METADATA
EMIZ-2018.9.16.4.dist-info/RECORD
EMIZ-2018.9.16.4.dist-info/WHEEL
EMIZ-2018.9.16.4.dist-info/top_level.txt
emiz/__init__.py
emiz/_parking_spots.py
emiz/dummy_miz.py
emiz/edit_miz.py
emiz/mission.py
emiz/mission_time.py
emiz/miz.py
emiz/new_miz.py
emiz/parking_spots.py
emiz/parse_parking_spots.py
emiz/sltp.py
emiz/validator.py
emiz/avwx/__init__.py
emiz/avwx/core.py
emiz/avwx/exceptions.py
emiz/avwx/metar.py
emiz/avwx/remarks.py
emiz/avwx/service.py
emiz/avwx/speech.py
emiz/avwx/static.py
emiz/avwx/stations.json
emiz/avwx/structs.py
emiz/avwx/summary.py
emiz/avwx/taf.py
emiz/avwx/translate.py
emiz/weather/__init__.py
emiz/weather/utils.py
emiz/weather/avwx/__init__.py
emiz/weather/avwx/avwx.py
emiz/weather/avwx/avwx_result.py
emiz/weather/avwx/exc.py
emiz/weather/awc/__init__.py
emiz/weather/awc/awc.py
emiz/weather/awc/awc_result.py
emiz/weather/awc/exc.py
emiz/weather/custom_metar/__init__.py
emiz/weather/custom_metar/custom_metar.py
emiz/weather/custom_metar/custom_metar_pressure.py
emiz/weather/mission_weather/__init__.py
emiz/weather/mission_weather/mission_weather.py
emiz/weather/mizfile/__init__.py
emiz/weather/mizfile/mizfile_get_metar.py
emiz/weather/mizfile/mizfile_set_metar.py
emiz/weather/noaa/__init__.py
test/__init__.py
test/conftest.py
test/test_edit_miz.py
test/test_imports.py
test/test_mission_time.py
test/test_miz.py
test/test_sltp.py
test/test_files/SDCM_1.4.0.127_csar.miz
test/test_files/TRG_KA50.miz
test/test_files/TRMT_2.4.0.miz
test/test_files/TRMT_5.1.0-OVC-171220.miz
test/test_files/TRMT_6.4.3.miz
test/test_files/TRM_0.1.0.159_edit.miz
test/test_files/all_objects.miz
test/test_files/bad_zip_file.miz
test/test_files/clients.miz
test/test_files/duplicate_group_id.miz
test/test_files/empty.miz
test/test_files/icaos.txt
test/test_files/missing_files.miz
test/test_files/radios.miz
test/test_files/radios2.miz
test/test_files/test_158.miz
test/test_files/time.miz
test/test_files/weather.miz
test/test_files/sltp/diff/dic1
test/test_files/sltp/diff/dic2
test/test_files/sltp/diff/dic3
