Metadata-Version: 2.1
Name: EMIZ
Version: 2018.9.16.4
Summary: Set of tools for the DCS mission builder
Home-page: https://github.com/132nd-etcher/EMIZ
Author: 132nd-etcher
Author-email: emiz@daribouca.net
License: GPLv3
Download-URL: https://github.com/132nd-etcher/EMIZ/releases
Platform: win32
Classifier: Development Status :: 3 - Alpha
Classifier: Topic :: Utilities
Classifier: License :: OSI Approved :: GNU General Public License v3 (GPLv3)
Classifier: Environment :: Win32 (MS Windows)
Classifier: Natural Language :: English
Classifier: Operating System :: Microsoft :: Windows
Classifier: Operating System :: Microsoft :: Windows :: Windows 7
Classifier: Operating System :: Microsoft :: Windows :: Windows 8
Classifier: Operating System :: Microsoft :: Windows :: Windows 8.1
Classifier: Operating System :: Microsoft :: Windows :: Windows 10
Classifier: Programming Language :: Cython
Classifier: Programming Language :: Python
Classifier: Programming Language :: Python :: 3 :: Only
Classifier: Programming Language :: Python :: 3.6
Classifier: Programming Language :: Python :: Implementation
Classifier: Programming Language :: Python :: Implementation :: CPython
Classifier: Topic :: Games/Entertainment
Classifier: Topic :: Utilities
Requires-Python: >=3.6
Requires-Dist: certifi
Requires-Dist: chardet
Requires-Dist: click
Requires-Dist: idna
Requires-Dist: metar
Requires-Dist: mpmath
Requires-Dist: natsort
Requires-Dist: requests
Requires-Dist: urllib3
Requires-Dist: elib
Requires-Dist: ujson
Requires-Dist: pathvalidate
Requires-Dist: python-dateutil
Requires-Dist: dataclasses
Requires-Dist: xmltodict
